{
  "code": "N21000722",
  "name": "Crotlieve_D",
  "comment": "This JSON includes data for the area explorer app.",
  "type": "sdz",
  "count": 850,
  "parents": [
    {
      "code": "N10001001",
      "name": "Crotlieve",
      "type": "dea"
    },
    {
      "code": "N09000010",
      "name": "Newry, Mourne and Down",
      "type": "lgd"
    },
    {
      "code": "N92000002",
      "name": "Northern Ireland",
      "type": "ctry"
    }
  ],
  "children": [
    {
      "code": "N20003217",
      "name": "Crotlieve_D1",
      "type": "dz"
    },
    {
      "code": "N20003218",
      "name": "Crotlieve_D2",
      "type": "dz"
    },
    {
      "code": "N20003220",
      "name": "Crotlieve_D3",
      "type": "dz"
    }
  ],
  "bounds": [
    [-6.1337, 54.19],
    [-6.1506, 54.1994]
  ],
  "data": {
    "population": {
      "perc": {
        "2011": {
          "all": 100
        },
        "2021": {
          "all": 100
        }
      },
      "value": {
        "2011": {
          "all": 0
        },
        "change": {
          "all": "Inf"
        },
        "2021": {
          "all": 1719
        }
      },
      "value_rank": {
        "2011": {
          "all": 0
        },
        "2021": {
          "all": 681
        }
      }
    },
    "households": {
      "perc": {
        "2011": {
          "all_households": 100
        },
        "2021": {
          "all_households": 100
        }
      },
      "value": {
        "2011": {
          "all_households": 0
        },
        "change": {
          "all_households": "Inf"
        },
        "2021": {
          "all_households": 640
        }
      }
    },
    "general_health": {
      "perc": {
        "2011": {
          "bad": 100,
          "fair": 100,
          "good": 100,
          "very_bad": 100,
          "very_good": 100
        },
        "2021": {
          "bad": 4.416,
          "fair": 9.9942,
          "good": 26.2057,
          "very_bad": 1.5689,
          "very_good": 57.8152
        }
      }
    },
    "hh_size": {
      "perc": {
        "2011": {
          "five_people": 100,
          "four_people": 100,
          "one_person": 100,
          "three_people": 100,
          "two_people": 100
        },
        "2021": {
          "five_people": 12.6365,
          "four_people": 17.9407,
          "one_person": 26.053,
          "three_people": 17.4727,
          "two_people": 25.897
        }
      }
    },
    "highest_level_of_qualifications": {
      "perc": {
        "2011": {
          "apprenticeship": 100,
          "level_1_qualifications": 100,
          "level_2_qualifications": 100,
          "level_3_qualifications": 100,
          "level_4_qualifications_and_above": 100,
          "no_qualifications": 100,
          "other_qualifications": 100
        },
        "2021": {
          "apprenticeship": 8.8854,
          "level_1_qualifications": 3.9751,
          "level_2_qualifications": 14.3414,
          "level_3_qualifications": 17.0694,
          "level_4_qualifications_and_above": 32.3461,
          "no_qualifications": 21.9797,
          "other_qualifications": 1.403
        }
      }
    },
    "cob": {
      "perc": {
        "2011": {
          "england": 100,
          "northern_ireland": 100,
          "other_cob": 100,
          "republic_of_ireland": 100,
          "scotland": 100,
          "wales": 100
        },
        "2021": {
          "england": 3.3662,
          "northern_ireland": 88.9147,
          "other_cob": 3.2501,
          "republic_of_ireland": 3.076,
          "scotland": 1.2768,
          "wales": 0.1161
        }
      }
    },
    "mainlang": {
      "perc": {
        "2011": {
          "english": 100,
          "other_languages": 100
        },
        "2021": {
          "english": 98.1707,
          "other_languages": 1.8293
        }
      }
    },
    "age": {
      "perc": {
        "2011": {
          "a0to14": 100,
          "a15to39": 100,
          "a40to64": 100,
          "a65plus": 100
        },
        "2021": {
          "a0to14": 23.7071,
          "a15to39": 33.4108,
          "a40to64": 32.5392,
          "a65plus": 10.3428
        }
      }
    },
    "provision_care": {
      "perc": {
        "2011": {
          "a1to19_hours": 100,
          "a20to49_hours": 100,
          "a50plus_hours": 100,
          "no_care": 100
        },
        "2021": {
          "a1to19_hours": 5.1605,
          "a20to49_hours": 3.2725,
          "a50plus_hours": 4.0277,
          "no_care": 87.5393
        }
      }
    },
    "religion_or_religion_brought_up_in": {
      "perc": {
        "2011": {
          "catholic": 100,
          "none": 100,
          "other_religions": 100,
          "protestant_and_other_christian_including_christian_related": 100
        },
        "2021": {
          "catholic": 92.853,
          "none": 2.4985,
          "other_religions": 0.7554,
          "protestant_and_other_christian_including_christian_related": 3.8931
        }
      }
    },
    "sex": {
      "perc": {
        "2011": {
          "females": 100,
          "males": 100
        },
        "2021": {
          "females": 52.4695,
          "males": 47.5305
        }
      }
    },
    "BS": {
      "perc": {
        "2023": {
          "UC": 20,
          "JSA": 1.3333,
          "AA": 4,
          "PIP": 18.6667,
          "IS": 2.6667,
          "DLA": 6.6667,
          "ESA": 9.3333,
          "PC": 6.6667,
          "CA": 10.6667,
          "RP": 20
        },
        "2022": {
          "PIP": 17.5676,
          "UC": 17.5676,
          "IS": 4.0541,
          "DLA": 6.7568,
          "ESA": 10.8108,
          "JSA": 1.3514,
          "AA": 4.0541,
          "CA": 10.8108,
          "RP": 20.2703,
          "PC": 6.7568
        },
        "2017": {
          "DLA": 24.1935,
          "JSA": 3.2258,
          "PC": 9.6774,
          "PIP": 1.6129,
          "ESA": 12.9032,
          "UC": 0,
          "RP": 22.5806,
          "IS": 8.0645,
          "AA": 4.8387,
          "CA": 12.9032
        }
      },
      "value": {
        "2023": {
          "UC": 150,
          "JSA": 10,
          "AA": 30,
          "PIP": 140,
          "IS": 20,
          "DLA": 50,
          "ESA": 70,
          "PC": 50,
          "CA": 80,
          "RP": 150
        },
        "2022": {
          "PIP": 130,
          "UC": 130,
          "IS": 30,
          "DLA": 50,
          "ESA": 80,
          "JSA": 10,
          "AA": 30,
          "CA": 80,
          "RP": 150,
          "PC": 50
        },
        "2017": {
          "DLA": 150,
          "JSA": 20,
          "PC": 60,
          "PIP": 10,
          "ESA": 80,
          "UC": 0,
          "RP": 140,
          "IS": 50,
          "AA": 30,
          "CA": 80
        }
      }
    }
  },
  "hectares": 77,
  "grouped_data_nocompare": {
    "population": [
      {
        "group": "Crotlieve_D",
        "category": "all",
        "perc": 100
      }
    ],
    "households": [
      {
        "group": "Crotlieve_D",
        "category": "all_households",
        "perc": 100
      }
    ],
    "general_health": [
      {
        "group": "Crotlieve_D",
        "category": "bad",
        "perc": 4.416
      },
      {
        "group": "Crotlieve_D",
        "category": "fair",
        "perc": 9.9942
      },
      {
        "group": "Crotlieve_D",
        "category": "good",
        "perc": 26.2057
      },
      {
        "group": "Crotlieve_D",
        "category": "very_bad",
        "perc": 1.5689
      },
      {
        "group": "Crotlieve_D",
        "category": "very_good",
        "perc": 57.8152
      }
    ],
    "hh_size": [
      {
        "group": "Crotlieve_D",
        "category": "five_people",
        "perc": 12.6365
      },
      {
        "group": "Crotlieve_D",
        "category": "four_people",
        "perc": 17.9407
      },
      {
        "group": "Crotlieve_D",
        "category": "one_person",
        "perc": 26.053
      },
      {
        "group": "Crotlieve_D",
        "category": "three_people",
        "perc": 17.4727
      },
      {
        "group": "Crotlieve_D",
        "category": "two_people",
        "perc": 25.897
      }
    ],
    "highest_level_of_qualifications": [
      {
        "group": "Crotlieve_D",
        "category": "apprenticeship",
        "perc": 8.8854
      },
      {
        "group": "Crotlieve_D",
        "category": "level_1_qualifications",
        "perc": 3.9751
      },
      {
        "group": "Crotlieve_D",
        "category": "level_2_qualifications",
        "perc": 14.3414
      },
      {
        "group": "Crotlieve_D",
        "category": "level_3_qualifications",
        "perc": 17.0694
      },
      {
        "group": "Crotlieve_D",
        "category": "level_4_qualifications_and_above",
        "perc": 32.3461
      },
      {
        "group": "Crotlieve_D",
        "category": "no_qualifications",
        "perc": 21.9797
      },
      {
        "group": "Crotlieve_D",
        "category": "other_qualifications",
        "perc": 1.403
      }
    ],
    "cob": [
      {
        "group": "Crotlieve_D",
        "category": "england",
        "perc": 3.3662
      },
      {
        "group": "Crotlieve_D",
        "category": "northern_ireland",
        "perc": 88.9147
      },
      {
        "group": "Crotlieve_D",
        "category": "other_cob",
        "perc": 3.2501
      },
      {
        "group": "Crotlieve_D",
        "category": "republic_of_ireland",
        "perc": 3.076
      },
      {
        "group": "Crotlieve_D",
        "category": "scotland",
        "perc": 1.2768
      },
      {
        "group": "Crotlieve_D",
        "category": "wales",
        "perc": 0.1161
      }
    ],
    "mainlang": [
      {
        "group": "Crotlieve_D",
        "category": "english",
        "perc": 98.1707
      },
      {
        "group": "Crotlieve_D",
        "category": "other_languages",
        "perc": 1.8293
      }
    ],
    "age": [
      {
        "group": "Crotlieve_D",
        "category": "a0to14",
        "perc": 23.7071
      },
      {
        "group": "Crotlieve_D",
        "category": "a15to39",
        "perc": 33.4108
      },
      {
        "group": "Crotlieve_D",
        "category": "a40to64",
        "perc": 32.5392
      },
      {
        "group": "Crotlieve_D",
        "category": "a65plus",
        "perc": 10.3428
      }
    ],
    "provision_care": [
      {
        "group": "Crotlieve_D",
        "category": "a1to19_hours",
        "perc": 5.1605
      },
      {
        "group": "Crotlieve_D",
        "category": "a20to49_hours",
        "perc": 3.2725
      },
      {
        "group": "Crotlieve_D",
        "category": "a50plus_hours",
        "perc": 4.0277
      },
      {
        "group": "Crotlieve_D",
        "category": "no_care",
        "perc": 87.5393
      }
    ],
    "religion_or_religion_brought_up_in": [
      {
        "group": "Crotlieve_D",
        "category": "catholic",
        "perc": 92.853
      },
      {
        "group": "Crotlieve_D",
        "category": "none",
        "perc": 2.4985
      },
      {
        "group": "Crotlieve_D",
        "category": "other_religions",
        "perc": 0.7554
      },
      {
        "group": "Crotlieve_D",
        "category": "protestant_and_other_christian_including_christian_related",
        "perc": 3.8931
      }
    ],
    "sex": [
      {
        "group": "Crotlieve_D",
        "category": "females",
        "perc": 52.4695
      },
      {
        "group": "Crotlieve_D",
        "category": "males",
        "perc": 47.5305
      }
    ],
    "BS": {
      "2023": [
        {
          "group": "Crotlieve_D",
          "category": "UC",
          "perc": 20
        },
        {
          "group": "Crotlieve_D",
          "category": "JSA",
          "perc": 1.3333
        },
        {
          "group": "Crotlieve_D",
          "category": "AA",
          "perc": 4
        },
        {
          "group": "Crotlieve_D",
          "category": "PIP",
          "perc": 18.6667
        },
        {
          "group": "Crotlieve_D",
          "category": "IS",
          "perc": 2.6667
        },
        {
          "group": "Crotlieve_D",
          "category": "DLA",
          "perc": 6.6667
        },
        {
          "group": "Crotlieve_D",
          "category": "ESA",
          "perc": 9.3333
        },
        {
          "group": "Crotlieve_D",
          "category": "PC",
          "perc": 6.6667
        },
        {
          "group": "Crotlieve_D",
          "category": "CA",
          "perc": 10.6667
        },
        {
          "group": "Crotlieve_D",
          "category": "RP",
          "perc": 20
        }
      ],
      "2022": [
        {
          "group": "Crotlieve_D",
          "category": "PIP",
          "perc": 17.5676
        },
        {
          "group": "Crotlieve_D",
          "category": "UC",
          "perc": 17.5676
        },
        {
          "group": "Crotlieve_D",
          "category": "IS",
          "perc": 4.0541
        },
        {
          "group": "Crotlieve_D",
          "category": "DLA",
          "perc": 6.7568
        },
        {
          "group": "Crotlieve_D",
          "category": "ESA",
          "perc": 10.8108
        },
        {
          "group": "Crotlieve_D",
          "category": "JSA",
          "perc": 1.3514
        },
        {
          "group": "Crotlieve_D",
          "category": "AA",
          "perc": 4.0541
        },
        {
          "group": "Crotlieve_D",
          "category": "CA",
          "perc": 10.8108
        },
        {
          "group": "Crotlieve_D",
          "category": "RP",
          "perc": 20.2703
        },
        {
          "group": "Crotlieve_D",
          "category": "PC",
          "perc": 6.7568
        }
      ],
      "2017": [
        {
          "group": "Crotlieve_D",
          "category": "DLA",
          "perc": 24.1935
        },
        {
          "group": "Crotlieve_D",
          "category": "JSA",
          "perc": 3.2258
        },
        {
          "group": "Crotlieve_D",
          "category": "PC",
          "perc": 9.6774
        },
        {
          "group": "Crotlieve_D",
          "category": "PIP",
          "perc": 1.6129
        },
        {
          "group": "Crotlieve_D",
          "category": "ESA",
          "perc": 12.9032
        },
        {
          "group": "Crotlieve_D",
          "category": "UC",
          "perc": 0
        },
        {
          "group": "Crotlieve_D",
          "category": "RP",
          "perc": 22.5806
        },
        {
          "group": "Crotlieve_D",
          "category": "IS",
          "perc": 8.0645
        },
        {
          "group": "Crotlieve_D",
          "category": "AA",
          "perc": 4.8387
        },
        {
          "group": "Crotlieve_D",
          "category": "CA",
          "perc": 12.9032
        }
      ]
    }
  },
  "grouped_data_timecompare": {
    "population": [
      {
        "group": 2021,
        "category": "all",
        "perc": 100
      }
    ],
    "households": [
      {
        "group": 2021,
        "category": "all_households",
        "perc": 100
      }
    ],
    "general_health": [
      {
        "group": 2021,
        "category": "bad",
        "perc": 4.416
      },
      {
        "group": 2021,
        "category": "fair",
        "perc": 9.9942
      },
      {
        "group": 2021,
        "category": "good",
        "perc": 26.2057
      },
      {
        "group": 2021,
        "category": "very_bad",
        "perc": 1.5689
      },
      {
        "group": 2021,
        "category": "very_good",
        "perc": 57.8152
      }
    ],
    "hh_size": [
      {
        "group": 2021,
        "category": "five_people",
        "perc": 12.6365
      },
      {
        "group": 2021,
        "category": "four_people",
        "perc": 17.9407
      },
      {
        "group": 2021,
        "category": "one_person",
        "perc": 26.053
      },
      {
        "group": 2021,
        "category": "three_people",
        "perc": 17.4727
      },
      {
        "group": 2021,
        "category": "two_people",
        "perc": 25.897
      }
    ],
    "highest_level_of_qualifications": [
      {
        "group": 2021,
        "category": "apprenticeship",
        "perc": 8.8854
      },
      {
        "group": 2021,
        "category": "level_1_qualifications",
        "perc": 3.9751
      },
      {
        "group": 2021,
        "category": "level_2_qualifications",
        "perc": 14.3414
      },
      {
        "group": 2021,
        "category": "level_3_qualifications",
        "perc": 17.0694
      },
      {
        "group": 2021,
        "category": "level_4_qualifications_and_above",
        "perc": 32.3461
      },
      {
        "group": 2021,
        "category": "no_qualifications",
        "perc": 21.9797
      },
      {
        "group": 2021,
        "category": "other_qualifications",
        "perc": 1.403
      }
    ],
    "cob": [
      {
        "group": 2021,
        "category": "england",
        "perc": 3.3662
      },
      {
        "group": 2021,
        "category": "northern_ireland",
        "perc": 88.9147
      },
      {
        "group": 2021,
        "category": "other_cob",
        "perc": 3.2501
      },
      {
        "group": 2021,
        "category": "republic_of_ireland",
        "perc": 3.076
      },
      {
        "group": 2021,
        "category": "scotland",
        "perc": 1.2768
      },
      {
        "group": 2021,
        "category": "wales",
        "perc": 0.1161
      }
    ],
    "mainlang": [
      {
        "group": 2021,
        "category": "english",
        "perc": 98.1707
      },
      {
        "group": 2021,
        "category": "other_languages",
        "perc": 1.8293
      }
    ],
    "age": [
      {
        "group": 2021,
        "category": "a0to14",
        "perc": 23.7071
      },
      {
        "group": 2021,
        "category": "a15to39",
        "perc": 33.4108
      },
      {
        "group": 2021,
        "category": "a40to64",
        "perc": 32.5392
      },
      {
        "group": 2021,
        "category": "a65plus",
        "perc": 10.3428
      }
    ],
    "provision_care": [
      {
        "group": 2021,
        "category": "a1to19_hours",
        "perc": 5.1605
      },
      {
        "group": 2021,
        "category": "a20to49_hours",
        "perc": 3.2725
      },
      {
        "group": 2021,
        "category": "a50plus_hours",
        "perc": 4.0277
      },
      {
        "group": 2021,
        "category": "no_care",
        "perc": 87.5393
      }
    ],
    "religion_or_religion_brought_up_in": [
      {
        "group": 2021,
        "category": "catholic",
        "perc": 92.853
      },
      {
        "group": 2021,
        "category": "none",
        "perc": 2.4985
      },
      {
        "group": 2021,
        "category": "other_religions",
        "perc": 0.7554
      },
      {
        "group": 2021,
        "category": "protestant_and_other_christian_including_christian_related",
        "perc": 3.8931
      }
    ],
    "sex": [
      {
        "group": 2021,
        "category": "females",
        "perc": 52.4695
      },
      {
        "group": 2021,
        "category": "males",
        "perc": 47.5305
      }
    ],
    "BS": [
      {
        "group": "2023",
        "category": "UC",
        "perc": 20
      },
      {
        "group": "2023",
        "category": "JSA",
        "perc": 1.3333
      },
      {
        "group": "2023",
        "category": "AA",
        "perc": 4
      },
      {
        "group": "2023",
        "category": "PIP",
        "perc": 18.6667
      },
      {
        "group": "2023",
        "category": "IS",
        "perc": 2.6667
      },
      {
        "group": "2023",
        "category": "DLA",
        "perc": 6.6667
      },
      {
        "group": "2023",
        "category": "ESA",
        "perc": 9.3333
      },
      {
        "group": "2023",
        "category": "PC",
        "perc": 6.6667
      },
      {
        "group": "2023",
        "category": "CA",
        "perc": 10.6667
      },
      {
        "group": "2023",
        "category": "RP",
        "perc": 20
      },
      {
        "group": "2022",
        "category": "PIP",
        "perc": 17.5676
      },
      {
        "group": "2022",
        "category": "UC",
        "perc": 17.5676
      },
      {
        "group": "2022",
        "category": "IS",
        "perc": 4.0541
      },
      {
        "group": "2022",
        "category": "DLA",
        "perc": 6.7568
      },
      {
        "group": "2022",
        "category": "ESA",
        "perc": 10.8108
      },
      {
        "group": "2022",
        "category": "JSA",
        "perc": 1.3514
      },
      {
        "group": "2022",
        "category": "AA",
        "perc": 4.0541
      },
      {
        "group": "2022",
        "category": "CA",
        "perc": 10.8108
      },
      {
        "group": "2022",
        "category": "RP",
        "perc": 20.2703
      },
      {
        "group": "2022",
        "category": "PC",
        "perc": 6.7568
      },
      {
        "group": "2017",
        "category": "DLA",
        "perc": 24.1935
      },
      {
        "group": "2017",
        "category": "JSA",
        "perc": 3.2258
      },
      {
        "group": "2017",
        "category": "PC",
        "perc": 9.6774
      },
      {
        "group": "2017",
        "category": "PIP",
        "perc": 1.6129
      },
      {
        "group": "2017",
        "category": "ESA",
        "perc": 12.9032
      },
      {
        "group": "2017",
        "category": "UC",
        "perc": 0
      },
      {
        "group": "2017",
        "category": "RP",
        "perc": 22.5806
      },
      {
        "group": "2017",
        "category": "IS",
        "perc": 8.0645
      },
      {
        "group": "2017",
        "category": "AA",
        "perc": 4.8387
      },
      {
        "group": "2017",
        "category": "CA",
        "perc": 12.9032
      }
    ]
  },
  "grouped_data_areacompare": {
    "population": [
      {
        "group": "Crotlieve_D",
        "category": "all",
        "perc": 100
      },
      {
        "group": "Northern Ireland",
        "category": "all",
        "perc": 100
      }
    ],
    "households": [
      {
        "group": "Crotlieve_D",
        "category": "all_households",
        "perc": 100
      },
      {
        "group": "Northern Ireland",
        "category": "all_households",
        "perc": 100
      }
    ],
    "general_health": [
      {
        "group": "Crotlieve_D",
        "category": "bad",
        "perc": 4.416
      },
      {
        "group": "Crotlieve_D",
        "category": "fair",
        "perc": 9.9942
      },
      {
        "group": "Crotlieve_D",
        "category": "good",
        "perc": 26.2057
      },
      {
        "group": "Crotlieve_D",
        "category": "very_bad",
        "perc": 1.5689
      },
      {
        "group": "Crotlieve_D",
        "category": "very_good",
        "perc": 57.8152
      },
      {
        "group": "Northern Ireland",
        "category": "bad",
        "perc": 5.7253
      },
      {
        "group": "Northern Ireland",
        "category": "fair",
        "perc": 13.6606
      },
      {
        "group": "Northern Ireland",
        "category": "good",
        "perc": 28.6906
      },
      {
        "group": "Northern Ireland",
        "category": "very_bad",
        "perc": 1.9477
      },
      {
        "group": "Northern Ireland",
        "category": "very_good",
        "perc": 49.9757
      }
    ],
    "hh_size": [
      {
        "group": "Crotlieve_D",
        "category": "five_people",
        "perc": 12.6365
      },
      {
        "group": "Crotlieve_D",
        "category": "four_people",
        "perc": 17.9407
      },
      {
        "group": "Crotlieve_D",
        "category": "one_person",
        "perc": 26.053
      },
      {
        "group": "Crotlieve_D",
        "category": "three_people",
        "perc": 17.4727
      },
      {
        "group": "Crotlieve_D",
        "category": "two_people",
        "perc": 25.897
      },
      {
        "group": "Northern Ireland",
        "category": "five_people",
        "perc": 8.9534
      },
      {
        "group": "Northern Ireland",
        "category": "four_people",
        "perc": 13.7536
      },
      {
        "group": "Northern Ireland",
        "category": "one_person",
        "perc": 30.5213
      },
      {
        "group": "Northern Ireland",
        "category": "three_people",
        "perc": 16.3433
      },
      {
        "group": "Northern Ireland",
        "category": "two_people",
        "perc": 30.4284
      }
    ],
    "highest_level_of_qualifications": [
      {
        "group": "Crotlieve_D",
        "category": "apprenticeship",
        "perc": 8.8854
      },
      {
        "group": "Crotlieve_D",
        "category": "level_1_qualifications",
        "perc": 3.9751
      },
      {
        "group": "Crotlieve_D",
        "category": "level_2_qualifications",
        "perc": 14.3414
      },
      {
        "group": "Crotlieve_D",
        "category": "level_3_qualifications",
        "perc": 17.0694
      },
      {
        "group": "Crotlieve_D",
        "category": "level_4_qualifications_and_above",
        "perc": 32.3461
      },
      {
        "group": "Crotlieve_D",
        "category": "no_qualifications",
        "perc": 21.9797
      },
      {
        "group": "Crotlieve_D",
        "category": "other_qualifications",
        "perc": 1.403
      },
      {
        "group": "Northern Ireland",
        "category": "apprenticeship",
        "perc": 6.3622
      },
      {
        "group": "Northern Ireland",
        "category": "level_1_qualifications",
        "perc": 5.9006
      },
      {
        "group": "Northern Ireland",
        "category": "level_2_qualifications",
        "perc": 13.6104
      },
      {
        "group": "Northern Ireland",
        "category": "level_3_qualifications",
        "perc": 15.9766
      },
      {
        "group": "Northern Ireland",
        "category": "level_4_qualifications_and_above",
        "perc": 32.1066
      },
      {
        "group": "Northern Ireland",
        "category": "no_qualifications",
        "perc": 23.8077
      },
      {
        "group": "Northern Ireland",
        "category": "other_qualifications",
        "perc": 2.2358
      }
    ],
    "cob": [
      {
        "group": "Crotlieve_D",
        "category": "england",
        "perc": 3.3662
      },
      {
        "group": "Crotlieve_D",
        "category": "northern_ireland",
        "perc": 88.9147
      },
      {
        "group": "Crotlieve_D",
        "category": "other_cob",
        "perc": 3.2501
      },
      {
        "group": "Crotlieve_D",
        "category": "republic_of_ireland",
        "perc": 3.076
      },
      {
        "group": "Crotlieve_D",
        "category": "scotland",
        "perc": 1.2768
      },
      {
        "group": "Crotlieve_D",
        "category": "wales",
        "perc": 0.1161
      },
      {
        "group": "Northern Ireland",
        "category": "england",
        "perc": 3.8325
      },
      {
        "group": "Northern Ireland",
        "category": "northern_ireland",
        "perc": 86.5016
      },
      {
        "group": "Northern Ireland",
        "category": "other_cob",
        "perc": 6.5303
      },
      {
        "group": "Northern Ireland",
        "category": "republic_of_ireland",
        "perc": 2.1205
      },
      {
        "group": "Northern Ireland",
        "category": "scotland",
        "perc": 0.8681
      },
      {
        "group": "Northern Ireland",
        "category": "wales",
        "perc": 0.1469
      }
    ],
    "mainlang": [
      {
        "group": "Crotlieve_D",
        "category": "english",
        "perc": 98.1707
      },
      {
        "group": "Crotlieve_D",
        "category": "other_languages",
        "perc": 1.8293
      },
      {
        "group": "Northern Ireland",
        "category": "english",
        "perc": 95.3662
      },
      {
        "group": "Northern Ireland",
        "category": "other_languages",
        "perc": 4.6338
      }
    ],
    "age": [
      {
        "group": "Crotlieve_D",
        "category": "a0to14",
        "perc": 23.7071
      },
      {
        "group": "Crotlieve_D",
        "category": "a15to39",
        "perc": 33.4108
      },
      {
        "group": "Crotlieve_D",
        "category": "a40to64",
        "perc": 32.5392
      },
      {
        "group": "Crotlieve_D",
        "category": "a65plus",
        "perc": 10.3428
      },
      {
        "group": "Northern Ireland",
        "category": "a0to14",
        "perc": 19.1896
      },
      {
        "group": "Northern Ireland",
        "category": "a15to39",
        "perc": 31.23
      },
      {
        "group": "Northern Ireland",
        "category": "a40to64",
        "perc": 32.4261
      },
      {
        "group": "Northern Ireland",
        "category": "a65plus",
        "perc": 17.1543
      }
    ],
    "provision_care": [
      {
        "group": "Crotlieve_D",
        "category": "a1to19_hours",
        "perc": 5.1605
      },
      {
        "group": "Crotlieve_D",
        "category": "a20to49_hours",
        "perc": 3.2725
      },
      {
        "group": "Crotlieve_D",
        "category": "a50plus_hours",
        "perc": 4.0277
      },
      {
        "group": "Crotlieve_D",
        "category": "no_care",
        "perc": 87.5393
      },
      {
        "group": "Northern Ireland",
        "category": "a1to19_hours",
        "perc": 5.6322
      },
      {
        "group": "Northern Ireland",
        "category": "a20to49_hours",
        "perc": 2.9479
      },
      {
        "group": "Northern Ireland",
        "category": "a50plus_hours",
        "perc": 3.8389
      },
      {
        "group": "Northern Ireland",
        "category": "no_care",
        "perc": 87.581
      }
    ],
    "religion_or_religion_brought_up_in": [
      {
        "group": "Crotlieve_D",
        "category": "catholic",
        "perc": 92.853
      },
      {
        "group": "Crotlieve_D",
        "category": "none",
        "perc": 2.4985
      },
      {
        "group": "Crotlieve_D",
        "category": "other_religions",
        "perc": 0.7554
      },
      {
        "group": "Crotlieve_D",
        "category": "protestant_and_other_christian_including_christian_related",
        "perc": 3.8931
      },
      {
        "group": "Northern Ireland",
        "category": "catholic",
        "perc": 45.7002
      },
      {
        "group": "Northern Ireland",
        "category": "none",
        "perc": 9.3192
      },
      {
        "group": "Northern Ireland",
        "category": "other_religions",
        "perc": 1.4982
      },
      {
        "group": "Northern Ireland",
        "category": "protestant_and_other_christian_including_christian_related",
        "perc": 43.4824
      }
    ],
    "sex": [
      {
        "group": "Crotlieve_D",
        "category": "females",
        "perc": 52.4695
      },
      {
        "group": "Crotlieve_D",
        "category": "males",
        "perc": 47.5305
      },
      {
        "group": "Northern Ireland",
        "category": "females",
        "perc": 50.8121
      },
      {
        "group": "Northern Ireland",
        "category": "males",
        "perc": 49.1879
      }
    ],
    "BS": {
      "2023": [
        {
          "group": "Crotlieve_D",
          "category": "UC",
          "perc": 20
        },
        {
          "group": "Crotlieve_D",
          "category": "JSA",
          "perc": 1.3333
        },
        {
          "group": "Crotlieve_D",
          "category": "AA",
          "perc": 4
        },
        {
          "group": "Crotlieve_D",
          "category": "PIP",
          "perc": 18.6667
        },
        {
          "group": "Crotlieve_D",
          "category": "IS",
          "perc": 2.6667
        },
        {
          "group": "Crotlieve_D",
          "category": "DLA",
          "perc": 6.6667
        },
        {
          "group": "Crotlieve_D",
          "category": "ESA",
          "perc": 9.3333
        },
        {
          "group": "Crotlieve_D",
          "category": "PC",
          "perc": 6.6667
        },
        {
          "group": "Crotlieve_D",
          "category": "CA",
          "perc": 10.6667
        },
        {
          "group": "Crotlieve_D",
          "category": "RP",
          "perc": 20
        },
        {
          "group": "Northern Ireland",
          "category": "DLA",
          "perc": 7.0487
        },
        {
          "group": "Northern Ireland",
          "category": "UC",
          "perc": 14.3332
        },
        {
          "group": "Northern Ireland",
          "category": "PIP",
          "perc": 17.9194
        },
        {
          "group": "Northern Ireland",
          "category": "RP",
          "perc": 30.3024
        },
        {
          "group": "Northern Ireland",
          "category": "IS",
          "perc": 1.3478
        },
        {
          "group": "Northern Ireland",
          "category": "JSA",
          "perc": 0.5376
        },
        {
          "group": "Northern Ireland",
          "category": "ESA",
          "perc": 10.0161
        },
        {
          "group": "Northern Ireland",
          "category": "PC",
          "perc": 5.8381
        },
        {
          "group": "Northern Ireland",
          "category": "CA",
          "perc": 7.3145
        },
        {
          "group": "Northern Ireland",
          "category": "AA",
          "perc": 5.3421
        }
      ],
      "2022": [
        {
          "group": "Crotlieve_D",
          "category": "PIP",
          "perc": 17.5676
        },
        {
          "group": "Crotlieve_D",
          "category": "UC",
          "perc": 17.5676
        },
        {
          "group": "Crotlieve_D",
          "category": "IS",
          "perc": 4.0541
        },
        {
          "group": "Crotlieve_D",
          "category": "DLA",
          "perc": 6.7568
        },
        {
          "group": "Crotlieve_D",
          "category": "ESA",
          "perc": 10.8108
        },
        {
          "group": "Crotlieve_D",
          "category": "JSA",
          "perc": 1.3514
        },
        {
          "group": "Crotlieve_D",
          "category": "AA",
          "perc": 4.0541
        },
        {
          "group": "Crotlieve_D",
          "category": "CA",
          "perc": 10.8108
        },
        {
          "group": "Crotlieve_D",
          "category": "RP",
          "perc": 20.2703
        },
        {
          "group": "Crotlieve_D",
          "category": "PC",
          "perc": 6.7568
        },
        {
          "group": "Northern Ireland",
          "category": "DLA",
          "perc": 7.3012
        },
        {
          "group": "Northern Ireland",
          "category": "RP",
          "perc": 30.5158
        },
        {
          "group": "Northern Ireland",
          "category": "IS",
          "perc": 1.6362
        },
        {
          "group": "Northern Ireland",
          "category": "UC",
          "perc": 13.1867
        },
        {
          "group": "Northern Ireland",
          "category": "AA",
          "perc": 5.2699
        },
        {
          "group": "Northern Ireland",
          "category": "PIP",
          "perc": 16.8093
        },
        {
          "group": "Northern Ireland",
          "category": "JSA",
          "perc": 0.7792
        },
        {
          "group": "Northern Ireland",
          "category": "CA",
          "perc": 7.4878
        },
        {
          "group": "Northern Ireland",
          "category": "ESA",
          "perc": 10.879
        },
        {
          "group": "Northern Ireland",
          "category": "PC",
          "perc": 6.1349
        }
      ],
      "2017": [
        {
          "group": "Crotlieve_D",
          "category": "DLA",
          "perc": 24.1935
        },
        {
          "group": "Crotlieve_D",
          "category": "JSA",
          "perc": 3.2258
        },
        {
          "group": "Crotlieve_D",
          "category": "PC",
          "perc": 9.6774
        },
        {
          "group": "Crotlieve_D",
          "category": "PIP",
          "perc": 1.6129
        },
        {
          "group": "Crotlieve_D",
          "category": "ESA",
          "perc": 12.9032
        },
        {
          "group": "Crotlieve_D",
          "category": "UC",
          "perc": 0
        },
        {
          "group": "Crotlieve_D",
          "category": "RP",
          "perc": 22.5806
        },
        {
          "group": "Crotlieve_D",
          "category": "IS",
          "perc": 8.0645
        },
        {
          "group": "Crotlieve_D",
          "category": "AA",
          "perc": 4.8387
        },
        {
          "group": "Crotlieve_D",
          "category": "CA",
          "perc": 12.9032
        },
        {
          "group": "Northern Ireland",
          "category": "DLA",
          "perc": 22.7152
        },
        {
          "group": "Northern Ireland",
          "category": "RP",
          "perc": 33.1043
        },
        {
          "group": "Northern Ireland",
          "category": "CA",
          "perc": 7.8752
        },
        {
          "group": "Northern Ireland",
          "category": "PIP",
          "perc": 0.8736
        },
        {
          "group": "Northern Ireland",
          "category": "ESA",
          "perc": 13.6602
        },
        {
          "group": "Northern Ireland",
          "category": "IS",
          "perc": 4.0767
        },
        {
          "group": "Northern Ireland",
          "category": "JSA",
          "perc": 3.4436
        },
        {
          "group": "Northern Ireland",
          "category": "UC",
          "perc": 0
        },
        {
          "group": "Northern Ireland",
          "category": "AA",
          "perc": 5.9436
        },
        {
          "group": "Northern Ireland",
          "category": "PC",
          "perc": 8.3076
        }
      ]
    }
  },
  "meta_data": {
    "BS": {
      "email": "",
      "title": "Benefit Statistics",
      "dataset_url": "https://data.nisra.gov.uk/table/BSSDZ",
      "last_updated": "2023-07-06"
    }
  }
}
